bitsoframework/__init__.py
bitsoframework/email.py
bitsoframework/middleware.py
bitsoframework/mixins.py
bitsoframework/models.py
bitsoframework/serializers.py
bitsoframework/vos.py
bitsoframework/activator/__init__.py
bitsoframework/activator/mixins.py
bitsoframework/authentication/__init__.py
bitsoframework/authentication/backend.py
bitsoframework/authentication/mixins.py
bitsoframework/authentication/serializers.py
bitsoframework/authored/__init__.py
bitsoframework/authored/models.py
bitsoframework/authored/serializers.py
bitsoframework/authored/settings.py
bitsoframework/aws/__init__.py
bitsoframework/aws/s3.py
bitsoframework/batch/__init__.py
bitsoframework/brazil/__init__.py
bitsoframework/brazil/cnpj.py
bitsoframework/copyable/__init__.py
bitsoframework/copyable/models.py
bitsoframework/db/__init__.py
bitsoframework/db/routers.py
bitsoframework/drf/__init__.py
bitsoframework/drf/filters.py
bitsoframework/drf/utils.py
bitsoframework/geo/__init__.py
bitsoframework/geo/serializers.py
bitsoframework/google/__init__.py
bitsoframework/google/firebase/__init__.py
bitsoframework/google/firestore/__init__.py
bitsoframework/google/firestore/services.py
bitsoframework/google/maps/__init__.py
bitsoframework/google/maps/models.py
bitsoframework/google/maps/services.py
bitsoframework/indexable/__init__.py
bitsoframework/indexable/mixins.py
bitsoframework/indexable/models.py
bitsoframework/media/__init__.py
bitsoframework/media/checksum.py
bitsoframework/media/content_type.py
bitsoframework/media/filterset.py
bitsoframework/media/mixins.py
bitsoframework/media/models.py
bitsoframework/media/path_resolvers.py
bitsoframework/media/registry.py
bitsoframework/media/serializers.py
bitsoframework/media/services.py
bitsoframework/media/settings.py
bitsoframework/media/utils.py
bitsoframework/media/vos.py
bitsoframework/media/audio/__init__.py
bitsoframework/media/audio/admin.py
bitsoframework/media/audio/mixins.py
bitsoframework/media/audio/models.py
bitsoframework-1.0.91.dist-info/METADATA
bitsoframework-1.0.91.dist-info/WHEEL
bitsoframework-1.0.91.dist-info/top_level.txt
bitsoframework-1.0.91.dist-info/RECORD
