Metadata-Version: 2.1
Name: bitsoframework
Version: 1.0.91
Summary: A python companion library for the BITSO Framework
Author: BITSO Framework
Author-email: bitsoframework@gmail.com
Classifier: Programming Language :: Python :: 3
Classifier: License :: OSI Approved :: MIT License
Classifier: Operating System :: OS Independent
